{
  "computers": [
    {
      "id": 1,
      "modele": "Latitude 3500 - 15.6",
      "marque": "Dell",
      "type": "Portable",
      "category": "Bureautique",
      "prixAchat": 120.88,
      "prixVente": 300.1,
      "dateEntreStock": " 2012-04-23T18:25:43.511Z"
    },
    {
      "id": 7,
      "modele": "mac",
      "marque": "Apple",
      "type": "Tablette hybride",
      "category": "Premier prix",
      "prixAchat": 423,
      "prixVente": 420,
      "dateEntreStock": "2020-07-02T16:15:00.130Z"
    },
    {
      "id": 8,
      "modele": "Vostro",
      "marque": "Dell",
      "type": "Portable",
      "category": "Gaming",
      "prixAchat": 480,
      "prixVente": 655,
      "dateEntreStock": "2020-07-02T16:32:44.350Z"
    }
  ]
}